xorc/__init__.py
XORc-1.0.8.dist-info/METADATA
XORc-1.0.8.dist-info/WHEEL
XORc-1.0.8.dist-info/entry_points.txt
XORc-1.0.8.dist-info/top_level.txt
XORc-1.0.8.dist-info/RECORD
