Metadata-Version: 2.1
Name: XORc
Version: 1.0.8
Summary: XORc is a simple python package to provide simple XOR encryption using XOR algorithms.
Home-page: https://github.com/bildsben/xorc
Author: bildsben
Author-email: ben.voisey2@gmail.com
License: MIT
Platform: UNKNOWN
Classifier: License :: OSI Approved :: MIT License
Classifier: Programming Language :: Python :: 3
Classifier: Programming Language :: Python :: 3.7
